Workbook

Sheet Counts and Profit
A1: Distributions of Students From k-12 ( Approximate ) | C1: Distribution Of Students From K-12 + Higher Ed Total ( Approximate ) | F1: US Student Counts
A2: K-5 (Elementary School) | B2: 0.4 | C2: Higher Education | D2: 0.2 | F2: Total | G2: 75000000
A3: 45816 | B3: 0.25 | C3: K-5 | D3: 0.32 | F3: Higher ED | G3: 19000000
A4: 45912 | B4: 0.35 | C4: 45816 | D4: 0.2 | F4: K-12 Pub | G4: 49600000
C5: 45912 | D5: 0.28 | F5: K-12 Private | G5: 5500000
A8: US Student Group | B8: Initial Focus ( 6-12 + Higher Ed, 68% ) | C8: Secondary Focus ( K-5, 32% ) | D8: Approximate Total Users | F8: Initial Focus V2 ( HS/College/6-8 ) 55% ) | G8: Secondary Focus ( K-5, 45% ) | I8: Future Audience Potential | J8: Approximate Count
A9: LMS Users US | B9: =D9*0.68 -> 47600000 | C9: =D9*0.32 -> 22400000 | D9: 70000000 | F9: =H9*0.35 -> 0 | G9: =H9*0.65 -> 0
A10: K-12 US + Higher Ed US | B10: =D10*0.68 -> 51000000 | C10: =D10*0.32 -> 24000000 | D10: 75000000 | F10: =H10*0.35 -> 0 | G10: =H10*0.65 -> 0 | I10: E-Learning Users Globally | J10: 350000000 | K10: 0
A13: Global Student Group | B13: Initial Focus ( 6-12 + Higher Ed, 68% ) | C13: Secondary Focus ( K-5, 32% ) | D13: Approximate Total Users
A14: LMS Users Globally | B14: =D14*0.68 -> 598400000 | C14: =D14*0.32 -> 281600000 | D14: =D15*0.55 -> 880000000
A15: K-12 + Higher Ed Globally | B15: =D15*0.68 -> 1088000000 | C15: =D15*0.32 -> 512000000 | D15: =1350000000+250000000 -> 1600000000
A18: Missouri Student Group | B18: Initial Focus ( 6-12+Higher Ed, 60% + Higher Ed ) | C18: HS/Higher Ed (35% K-12 + Higher Ed) | D18: Secondary Focus ( k-5, 40% ) | E18: Approximate Total Users
A19: LMS Users | B19: =B20 -> 868218.17 | C19: =C20 -> 634043.93 | D19: =D20 -> 374678.78 | E19: =E20 -> 1242896.9
A20: K-12 + Higher ED | B20: =sum(StudentCountsMO!D2, StudentCountsMO!G4 * 0.6) -> 868218.17 | C20: =sum(StudentCountsMO!D2, StudentCountsMO!G4 * 0.35) -> 634043.93 | D20: =sum(StudentCountsMO!G4*0.4) -> 374678.78 | E20: =StudentCountsMO!D2+StudentCountsMO!G2+StudentCountsMO!G3 -> 1242896.9
A22: KC Student Group | B22: Initial Focus ( 6-12+Higher Ed, 60% + Higher Ed ) | C22: HS/Higher Ed (35% K-12 + Higher Ed) | D22: Secondary Focus ( k-5, 40% ) | E22: Approximate Total Users
A23: LMS Users | B23: =B24 -> 188164 | C23: =C24 -> 149806.9 | D23: =D24 -> 102285.6 | E23: =E24 -> 316021
A24: K-12 + Higher ED | B24: =sum(StudentCountsMO!D3, 0.5*StudentCountsMO!G6) -> 188164 | C24: =sum(StudentCountsMO!D3, 0.35*StudentCountsMO!G6) -> 149806.9 | D24: =sum(StudentCountsMO!G6*0.4) -> 102285.6 | E24: =StudentCountsMO!G6+StudentCountsMO!D3 -> 316021
A25: KCPS
A28: Pricing | B28: "Freemium" ( May be charged to school ) | C28: "Membership Fee" Parents | D28: Add Ons
A29: Profit Estimates Target | B29: $0.25/m or 3$/yr | C29: 10$/m | D29: ?
A30: Profit Estimates Lower Cost Option, Maybe more users | B30: $0.1/m or 1.2$/yr | C30: 5.99$/m | D30: ?
A37: Yearly Profit Estimates US HS + Higher Ed | B37: 100% 1$/m 12$/yr | C37: 10% Earnings Rate @ 10$/m | D37: 30% Earnings Rate @ 10$/m | E37: 10% Earnings Rate 25$/m | F37: 30% Earnings Rate @ 25$/m
A38: 1% of Market | B38: =0.01*B41 -> 5712000 | C38: =0.01*C41 -> 5712000 | D38: =0.01*D41 -> 17136000 | E38: =0.01*E41 -> 14280000 | F38: =0.01*F41 -> 42840000
A39: 25% of Market | B39: =0.25*B41 -> 142800000 | C39: =0.25*C41 -> 142800000 | D39: =0.25*D41 -> 428400000 | E39: =0.25*E41 -> 357000000 | F39: =0.25*F41 -> 1071000000
A40: 51% of Market | B40: =0.51*B41 -> 291312000 | C40: =0.51*C41 -> 291312000 | D40: =0.51*D41 -> 873936000 | E40: =0.51*E41 -> 728280000 | F40: =0.51*F41 -> 2184840000
A41: 100% of Market | B41: =12*B9 -> 571200000 | C41: =120*B9*0.1 -> 571200000 | D41: =120*B9*0.3 -> 1713600000 | E41: =300*B9*0.1 -> 1428000000 | F41: =300*B9*0.3 -> 4284000000
A43: Yearly Profit Estimates Global HS + Higher Ed | B43: 100% 1$/m 12$/yr | C43: 10% Earnings Rate 10$/m | D43: 30% Earnings Rate @ 10$/m | E43: 10% Earnings Rate 25$/m | F43: 30% Earnings Rate @ 25$/m
B44: =0.01*B47 -> 71808000 | C44: =0.01*C47 -> 71808000 | D44: =0.01*D47 -> 215424000 | E44: =0.01*E47 -> 179520000 | F44: =0.01*F47 -> 179520000
A45: 25% of Market | B45: =0.25*B47 -> 1795200000 | C45: =0.25*C47 -> 1795200000 | D45: =0.25*D47 -> 5385600000 | E45: =0.25*E47 -> 4488000000 | F45: =0.25*F47 -> 4488000000
A46: 51% of Market | B46: =0.51*B47 -> 3662208000 | C46: =0.51*C47 -> 3662208000 | D46: =0.51*D47 -> 10986624000 | E46: =0.51*E47 -> 9155520000 | F46: =0.51*F47 -> 9155520000
A47: 100% of Market | B47: =12*B14 -> 7180800000 | C47: =120*B14*0.1 -> 7180800000 | D47: =120*B14*0.3 -> 21542400000 | E47: =300*B14*0.1 -> 17952000000 | F47: =300*B14*0.1 -> 17952000000
A50: Yearly Profit Estimates US K-8 | B50: 100% .1$/m 1.2$/yr | C50: 100% 1$/m | D50: 10% Earnings Rate @ 10$/m | E50: 30% Earnings Rate @ 10$/m
A51: 25% of Market | B51: =0.25*B53 -> 6720000 | C51: =C53*0.25 -> 67200000 | D51: =0.25*D53 -> 67200000 | E51: =0.25*E53 -> 201600000
A52: 51% of Market | B52: =0.51*B53 -> 13708800 | C52: =C53*0.51 -> 137088000 | D52: =0.51*D53 -> 137088000 | E52: =0.51*E53 -> 411264000
A53: 100% of Market | B53: =C9*1.2 -> 26880000 | C53: =C9*12 -> 268800000 | D53: =C9*120*0.1 -> 268800000 | E53: =C9*120*0.3 -> 806400000
A55: Yearly Profit Estimates Global K-8 | B55: 100% .1$/m 1.2$/yr | C55: 100% 1$/m | D55: 10% Earnings Rate @ 10$/m | E55: 30% Earnings Rate @ 10$/m
A56: 25% of Market | B56: =0.25*B58 -> 179520000 | C56: =0.25*C58 -> 1795200000 | D56: =0.25*D58 -> 1795200000 | E56: =0.25*E58 -> 2534400000
A57: 51% of Market | B57: =0.51*B58 -> 366220800 | C57: =C58*0.51 -> 3662208000 | D57: =0.51*D58 -> 3662208000 | E57: =0.51*E58 -> 5170176000
A58: 100% of Market | B58: =B14*1.2 -> 718080000 | C58: =B14*12 -> 7180800000 | D58: =B14*120*0.1 -> 7180800000 | E58: =C14*120*0.3 -> 10137600000
A60: Profit Summaries
A61: 100% HS/College Market, Freemium Users Only @0.1$/m | B61: =B62/10 -> 57120000
A62: 100% HS/College Market, Freemium Users Only @1$/m | B62: =B41 -> 571200000
A63: 100% K-8 Market, 30% Users Earnings Rate @ 10$/m | B63: =B53+E53 -> 833280000
A64: 25% of US Market HS, 30% Users Earnings Rate @ 10$/m | B64: =B39+D39 -> 571200000
A65: 100% of US Market HS, 30% Users Earnings Rate @ 10$/m | B65: =B41+D41 -> 2284800000
A66: 25% of US Market HS, 30% Users Earnings Rate @ 10$/m + 25% K-8 US Market, 30% Users Earnings Rate @ 10$/m | B66: =B39+D39+B51+E51 -> 779520000
A67: 100% of US Market HS, 30% Users Earnings Rate @ 10$/m + 100% K-8 US Market, 30% Users Earnings Rate @ 10$/m | B67: =B41+D41+B53+E53 -> 3118080000 | C67: Note that K-8 market has some competition from similar but not the same apps
A69: 100% HS Market, Freemium Users Only | B69: =B47 -> 7180800000
A70: 100% K-8 Market, 30% Users Earnings Rate @ 10$/m | B70: =B58+E58 -> 10855680000
A71: 25% of Global Market HS, 30% Users Earnings Rate @ 10$/m | B71: =B45+D45 -> 7180800000
A72: 100% of Global Market HS, 30% Users Earnings Rate @ 10$/m | B72: =B47+D47 -> 28723200000
A73: 25% of Global Market HS, 30% Users Earnings Rate @ 10$/m + 25% K-8 Global Market, 30% Users Earnings Rate @ 10$/m | B73: =B51+E51+B56+E56 -> 2922240000
A74: 100% of Global Market HS, 30% Users Earnings Rate @ 10$/m + 100% K-8 Global Market, 30% Users Earnings Rate @ 10$/m | B74: =B47+D47+B58+E58 -> 39578880000
A82: Profit Summaries V2 ( us / global needs updated )
A83: US | B83: 1% Market | C83: 100% Market
A84: 6-12 + Higher Ed Market, Freemium Users Only @0.1$/m | B84: =C84/10 -> 5712000 | C84: =B64/10 -> 57120000
A85: 6-12 + Higher Ed Market, Freemium Users Only @1$/m | B85: =C85/10 -> 57120000 | C85: =B64 -> 571200000
A86: 6-12 + Higher Ed Market, 30% Users Earnings Rate @ 10$/m | B86: =C86/10 -> 171360000 | C86: =D41 -> 1713600000
A87: 6-12 + Higher Ed Market, 10% Users Earnings Rate @ 5.99$/m | B87: =C87/100 -> 3421488 | C87: =B9*0.1*5.99*12 -> 342148800
A88: K-5 Market, Freemium Users Only @0.1$/m | B88: =C88/10 -> 2688000 | C88: =B53 -> 26880000
A89: K-5 Market, Freemium Users Only @1$/m | B89: =C89/10 -> 26880000 | C89: =C53 -> 268800000
A90: K-5 Market, 30% Users Earnings Rate @ 10$/m | B90: =C90/10 -> 80640000 | C90: =E53 -> 806400000
A91: Data Profit ( Optional, Complex, Potentially Risky ) | B91: ? | C91: ?
A92: K-5 & 6-12 + Higher Ed Market: Freemium @ 3$/yr, 10% Earning Rates $5.99 | B92: =SUM(B85, B86, B89, B90) -> 336000000 | C92: =SUM(C85, C86, C89, C90) -> 3360000000
A94: Global | B94: 1% Market | C94: 100% Market
A95: 6-12 + Higher Ed Market, Freemium Users Only @0.1$/m | B95: =C95/10 -> 71808000 | C95: =B47/10 -> 718080000 | D95: US 6-12 + Higher ed, b9 k-5 c9, global 6-12 b14, k-5 c14
A96: 6-12 + Higher Ed Market, Freemium Users Only @1$/m | B96: =C96/10 -> 718080000 | C96: =B47 -> 7180800000
A97: 6-12 + Higher Ed Market, 30% Users Earnings Rate @ 10$/m | B97: =C97/10 -> 2154240000 | C97: =D47 -> 21542400000
A98: 6-12 + Higher Ed Market, 10% Users Earnings Rate @ 5.99$/m | B98: =C98/100 -> 43012992 | C98: =B14*0.1*5.99*12 -> 4301299200
A99: K-5 Market, Freemium Users Only @0.1$/m | B99: =C99/10 -> 71808000 | C99: =B58 -> 718080000
A100: K-5 Market, Freemium Users Only @1$/m | B100: =C100/10 -> 718080000 | C100: =C58 -> 7180800000
A101: K-5 Market, 30% Users Earnings Rate @ 10$/m | B101: =C101/10 -> 1013760000 | C101: =E58 -> 10137600000
A102: Data Profit ( Optional, Complex, Potentially Risky ) | B102: ? | C102: ?
A103: K-5 & 6-12 + Higher Ed Market: Freemium @ 3$/yr, 10% Earning Rates $5.99 | B103: =sum(B96,B97,B100,B101) -> 4604160000 | C103: =sum(C96,C97,C100,C101) -> 46041600000
A105: MO | B105: 1% Market | C105: 100% Market
A106: 6-12 + Higher Ed Market, Freemium Users Only @0.1$/m | B106: =0.01*C106 -> 10418.618 | C106: =B19*1.2 -> 1041861.8
A107: 6-12 + Higher Ed Market, Freemium Users Only @.25$/m | B107: =0.01*C107 -> 26046.545 | C107: =B19*3 -> 2604654.5
A108: 6-12 + Higher Ed 10% Users Earnings Rate @ 10$/m | B108: =0.01*C108 -> 104186.18 | C108: =B19*0.1*120 -> 10418618
A109: 6-12 + Higher Ed 10% Users Earnings Rate @ 5.99$/m | B109: =0.01*C109 -> 62407.522 | C109: =B20*0.1*5.99*12 -> 6240752.2
A110: K-5 Market, Freemium Users Only @0.1$/m | B110: =0.01*C110 -> 4496.1454 | C110: =D19*1.2 -> 449614.54
A111: K-5 Market, Freemium Users Only @.25$/m | B111: =0.01*C111 -> 11240.363 | C111: =D19*3 -> 1124036.3
A112: K-5 Market, 10% Users Earnings Rate @ 5.99$/m | B112: =0.01*C112 -> 26931.911 | C112: =D19*0.1*5.99*12 -> 2693191.1
A113: Data Profit ( Optional, Complex, Potentially Risky ) | B113: ? | C113: ?
A114: 6-12 + Higher Ed (Freemium @ .1$/m + 10% Earning Rates @ 5.99$/m) | B114: =0.01*C114 -> 72826.14 | C114: =C106+C109 -> 7282614
A115: K-5 + 6-12 + Higher Ed (Freemium @ .1$/m + 10% Earning Rates @ 5.99$/m) | B115: =0.01*C115 -> 104254.2 | C115: =C106+C112+C110+C109 -> 10425420
A117: KC | B117: 1% Market | C117: 100% Market
A118: 6-12 + Higher Ed Market, Freemium Users Only @0.1$/m | B118: =0.01*C118 -> 2257.968 | C118: =1.2*B23 -> 225796.8
A119: 6-12 + Higher Ed Market, Freemium Users Only @.25$/m | B119: =0.01*C119 -> 5644.92 | C119: =3*B23 -> 564492
A120: 6-12 + Higher Ed 10% Users Earnings Rate @ 10$/m | B120: =0.01*C120 -> 22579.68 | C120: =0.1*B23*120 -> 2257968
A121: 6-12 + Higher Ed 10% Users Earnings Rate @ 5.99$/m | B121: =C121*0.01 -> 13525.228 | C121: =0.1*B23*5.99*12 -> 1352522.8
A122: K-5 Market, Freemium Users Only @0.1$/m | B122: =0.01*C122 -> 1227.4272 | C122: =D23*1.2 -> 122742.72
A123: K-5 Market, Freemium Users Only @.25$/m | B123: =0.01*C123 -> 3068.568 | C123: =D23*3 -> 306856.8
A124: K-5 Market, 10% Users Earnings Rate @ 5.99$/m | B124: =0.01*C124 -> 7352.2889 | C124: =D23*0.1*5.99*12 -> 735228.89
A125: Data Profit ( Optional, Complex, Potentially Risky ) | B125: ? | C125: ?
A126: 6-12 + Higher Ed (Freemium @ .1$/m + 10% Earning Rates @ 5.99/m) | B126: =0.01*C126 -> 15783.196 | C126: =C118+C121 -> 1578319.6
A127: K-5 + 6-12 + Higher Ed (Freemium @ .25$/yr + 10% Earning Rates @ 5.99$/m) | B127: =0.01*C127 -> 16482.604 | C127: =C118+C119+C122+C124 -> 1648260.4

Sheet Refined Targeting
A1: Really all schools but these are targeting types
A2: Inner City Schools, Schools with lower Engagement
A3: High End Schools, Competitive Players
A4: Rural Schools that may be easy targets

Sheet StudentCountsMO
A1: Colleges ( Missouri ) ( College Simply Source ) | F1: K-12 Missouri
A2: University of Missouri Columbia Columbia, MO add to list | Calculate my chances | B2: 31013 | C2: MO College Total (Less than max) | D2: =sum(B2:B37) -> 306200 | F2: Dese: Public Enrollment | G2: 859355 | H2: 16:1 Student To Teacher
A3: Missouri State University Springfield Springfield, MO add to list | Calculate my chances | B3: 23418 | C3: KC College Counts | D3: =sum(B6,B9,B18,B22,B23,B27,B31,B33,B34) -> 60307 | F3: Assuming 9% Private Enrollment | G3: =G2*0.09 -> 77341.95
A4: Saint Louis University Main Campus Saint Louis, MO add to list | Calculate my chances | B4: 17202 | F4: K-12 Missouri Total | G4: =SUM(G2:G3) -> 936696.95
A5: Washington University in St Louis Saint Louis, MO add to list | Calculate my chances | B5: 16500
A6: University of Missouri Kansas City Kansas City, MO add to list | Calculate my chances | B6: 15277 | F6: Kansas City K-12 Student Count Approximate Total, Assumes +9% Private School | G6: =SUM(G7:G25) + SUM(G7:G25)*0.09 -> 255714
A7: University of Missouri St Louis Saint Louis, MO add to list | Calculate my chances | B7: 14800 | F7: KC MO Public Schools | G7: 14000
A8: Saint Louis Community College Saint Louis, MO add to list | Calculate my chances | B8: 14627 | F8: Olathe (KS) Unified School District: | G8: 29000
A9: Metropolitan Community College Longview Lees Summit, MO add to list | Calculate my chances | B9: 12994 | F9: Shawnee Mission (KS) School District: | G9: 27000
A10: University of Central Missouri Warrensburg, MO add to list | Calculate my chances | B10: 12788 | F10: Blue Valley (KS) Unified School District: | G10: 22000
A11: Ozarks Technical Community College Springfield, MO add to list | Calculate my chances | B11: 11036 | F11: Kansas City, Kansas Public Schools (KCKPS): | G11: 21000
A12: Maryville University of Saint Louis Saint Louis, MO add to list | Calculate my chances | B12: 9883 | F12: North Kansas City (MO) School District: | G12: 19000
A13: Southeast Missouri State University Cape Girardeau, MO add to list | Calculate my chances | B13: 9686 | F13: Lee's Summit (MO) R-7 School District: | G13: 17000
A14: Northwest Missouri State University Maryville, MO add to list | Calculate my chances | B14: 9664 | F14: Independence School District | G14: 14000
A15: Webster University Saint Louis, MO add to list | Calculate my chances | B15: 7606 | F15: Park Hill School District | G15: 11000
A16: Lindenwood University Saint Charles, MO add to list | Calculate my chances | B16: 7288 | F16: Liberty Public Schools | G16: 12000
A17: Missouri University of Science and Technology Rolla, MO add to list | Calculate my chances | B17: 7156 | F17: Grandview C-4 School District | G17: 7000
A18: Park University Parkville, MO add to list | Calculate my chances | B18: 6634 | F18: Belton School District | G18: 5000
... A25: Missouri Southern State University Joplin, MO add to list | Calculate my chances | B25: 4090 | F25: Piper USD 203 | G25: 2600
A26: Crowder College Neosho, MO add to list | Calculate my chances | B26: 3865
A27: Midwestern Baptist Theological Seminary Kansas City, MO add to list | Calculate my chances | B27: 3840
A28: Missouri Western State University Saint Joseph, MO add to list | Calculate my chances | B28: 3817
A29: Jefferson College Hillsboro, MO add to list | Calculate my chances | B29: 3769
A30: State Fair Community College Sedalia, MO add to list | Calculate my chances | B30: 3754
A31: Grantham University Kansas City, KS add to list | Calculate my chances | B31: 3742
A32: Truman State University Kirksville, MO add to list | Calculate my chances | B32: 3636
A33: Metropolitan Community College Blue River Independence, Missouri add to list | Calculate my chances | B33: 3583
A34: Rockhurst University Kansas City, MO add to list | Calculate my chances | B34: 3496
A35: Three Rivers Community College Poplar Bluff, MO add to list | Calculate my chances | B35: 2682
A36: East Central College Union, MO add to list | Calculate my chances | B36: 2638
A37: Mineral Area College Park Hills, MO add to list | Calculate my chances | B37: 2389

Sheet Costs Integration
A1: Item | B1: Negotiable? | C1: Cost | D1: Anticipated total/yr 0-5000 Students | E1: Anticipated total/yr 5000-10000 Students | F1: Anticipated total/yr 10k-100k Students | G1: Anticipated total/yr 1,000,000 Students | H1: Anticipated total/yr 25,000,000 Students | I1: Accuracy Guess
A2: Ed.Link ( Potentially replacable with scale ) | B2: Yes but depends | C2: 10c/m/person to 1c/m/person | D2: =0.1*12*5000 -> 6000 | E2: =0.1*12*10000 -> 12000 | F2: =0.05*12*100000 -> 60000 | G2: =0.025*12*1000000 -> 300000 | H2: =0.01*12*25000000 -> 3000000 | I2: Somewhat Accurate
A3: Clever / Being on Clever Dashboard, Secure Sync? (optional) | B3: Yes but depends | C3: update: 0? cost is for sync | D3: 2k-11k | E3: 2k-11k | F3: 22k | G3: 220k | H3: 2mil | I3: Not very accurate
A4: Hosting / Compute | B4: Kind of? | C4: Complicated | D4: <1k/yr | E4: 1k/yr | F4: 3k/yr | G4: 10k/yr - 20k/yr | H4: 30k/yr - 300k/yr | I4: Depends on features and a lot of variables. Will have to see.
F5: $313.09/m Cloud Estimate ( Low End, Probably )
F6: Conservative resources
A9: Clever Grades and Assignments ( limited ) An alternative to Ed.Link ( they're using ed.link ) | B9: Probably | C9: 2k/school | D9: 2k-11k | E9: 2k-11k | F9: 22k | G9: 220k | H9: 2mil | I9: Not very accurate
C16: Estimated Students Per School | E16: 0-10 10c
C17: Elementary School: 200-800 students | E17: 10-100 5c
C18: Middle School: 500-1500 students | E18: 100-1mil 2.5c
C19: High School: 800-2500+ students | E19: 1mil+ 1c: 20,500/m?
C22: Assuming 1000 students/school
C23: 50 schools has 50,000 students
C24: =1000000 -> 1000000

Sheet Costs Staff
A1: Role | B1: Senior US | C1: Mid Level US | D1: Entry US | E1: Senior Overseas | F1: Mid Level Overseas | G1: Entry Overseas
A3: Software Engineer | B3: 125k-175k/yr ( Max 250k ) | C3: 70k-80k/yr | D3: 50-60k | E3: 50-100k/yr ( Freelance or FT ) | F3: 40k-50k/yr ( Freelance or FT ) | G3: 30-50k
A4: Designer/Animator | B4: 80-100k | C4: 60-90k | D4: 40-60k | E4: 35-40k
A5: Data Scientist | B5: Similar to S. Eng
A6: Machine Learning Specialist (Later) | B6: More Expensive than S. Eng
A7: Product Management | B7: 90-150k+ | C7: 60-90k | D7: 60-90k
A8: Quality Assurance & Testers | B8: 100k+ | C8: 70-100k | D8: 45-70k | E8: 35-40k
A9: Cyber Security | B9: 130k+ | C9: 90-130k | D9: 60-90k
A10: IT Support | B10: 80k+ | C10: 60-80k | D10: 40-60k
A11: Marketing: Digital, B2B, Inbound, Conferences, Networking | B11: 90k+ | C11: 60-90k | D11: 40-60k
A12: Sales ( Varies ), Related to Marketing Closers | B12: 90k+ | C12: 60-90k | D12: 40-60k
A13: Customer Service / Technical Support | B13: 50-60k | C13: 45-50k | D13: 35-45k
A14: Training, Onboarding, and Retention | B14: 60-75k+ | C14: 50-60k | D14: 45-50k
A15: HR/Recruitment | B15: 70-90k+ | C15: 60-70k | D15: 40-60k
A16: Consultants | B16: Varies
A17: Staffing Agencies | B17: Varies

Sheet Cost Software
A1: Software Category | B1: Software Example(s) | C1: Estimated Per User/Month Cost | D1: Notes
A2: Mobile Device Management (MDM) | B2: Microsoft Intune, Jamf Pro | C2: $5 - $15 | D2: Cost varies based on features and device count.
A3: Project Management Software | B3: Jira, Confluence / Atlassian | C3: $10 - $40 | D3: Tiered pricing based on features and user count.
A4: Google Workspace | B4: Business Standard, Enterprise | C4: $12 - $30 | D4: Pricing varies based on storage and features.
A5: 1Password | B5: Business, Teams | C5: $3 - $8 | D5: Offers secure password management for teams.
A6: Chat AI (Internal) | B6: Slack AI, Microsoft Teams Premium | C6: $5 - $15 | D6: Adds AI features like summarization and task generation to chat platforms.
A7: CRM / Salesforce | B7: Salesforce Sales Cloud, HubSpot CRM | C7: $25 - $150+ | D7: Salesforce has highly variable pricing based on editions and add-ons. HubSpot has a free tier, and paid tiers.
A8: Stock Assets (Images/Video) | B8: Adobe Stock, Shutterstock | C8: $20 - $50 (Subscription based) | D8: Monthly or annual subscriptions with varying download limits. Can also be priced per asset.
A9: AI Generation & Chat Tools | B9: ChatGPT Plus, Midjourney (Team) | C9: $20 - $50 | D9: ChatGPT Plus is a subscription. Midjourney is subscription based, and team plans cost more.
A10: CoPilot Coding AI | B10: GitHub Copilot, Amazon CodeWhisperer | C10: $10 - $20 | D10: Subscription-based coding assistance.
A11: Figma Design Software | B11: Professional, Organization | C11: $12 - $45 | D11: Tiered pricing based on collaboration and features.
A12: Adobe Suite | B12: Creative Cloud All Apps | C12: $60 - $90, Higher for business | D12: Business plans are higher to account for team collaboration.
